sereal/__init__.py
sereal/sereal.py
pysereal-0.1.8.dist-info/LICENSE
pysereal-0.1.8.dist-info/METADATA
pysereal-0.1.8.dist-info/WHEEL
pysereal-0.1.8.dist-info/top_level.txt
pysereal-0.1.8.dist-info/RECORD
